arelight/__init__.py
arelight/doc_provider.py
arelight/synonyms.py
arelight/utils.py
arelight/arekit/__init__.py
arelight/arekit/chunk_it.py
arelight/arekit/custom_sqlite_reader.py
arelight/arekit/joined_sqlite.py
arelight/arekit/parsed_row_service.py
arelight/arekit/sample_service.py
arelight/arekit/samples_io.py
arelight/arekit/utils_translator.py
arelight/backend/__init__.py
arelight/backend/d3js/__init__.py
arelight/backend/d3js/relations_graph_builder.py
arelight/backend/d3js/relations_graph_operations.py
arelight/backend/d3js/ui_web.py
arelight/backend/d3js/utils_graph.py
arelight/data/__init__.py
arelight/data/serializer_base.py
arelight/data/serializer_helper.py
arelight/data/repositories/__init__.py
arelight/data/repositories/base.py
arelight/data/repositories/sample.py
arelight/data/writers/__init__.py
arelight/data/writers/csv_native.py
arelight/data/writers/csv_pd.py
arelight/data/writers/json_opennre.py
arelight/data/writers/sqlite_native.py
arelight/ner/__init__.py
arelight/ner/base.py
arelight/ner/deep_pavlov.py
arelight/ner/obj_desc.py
arelight/pipelines/__init__.py
arelight/pipelines/data/__init__.py
arelight/pipelines/data/annot_pairs_nolabel.py
arelight/pipelines/demo/__init__.py
arelight/pipelines/demo/infer_bert.py
arelight/pipelines/demo/result.py
arelight/pipelines/demo/labels/__init__.py
arelight/pipelines/demo/labels/base.py
arelight/pipelines/demo/labels/formatter.py
arelight/pipelines/demo/labels/scalers.py
arelight/pipelines/items/__init__.py
arelight/pipelines/items/backend_d3js_graphs.py
arelight/pipelines/items/backend_d3js_operations.py
arelight/pipelines/items/entities_default.py
arelight/pipelines/items/entities_ner_dp.py
arelight/pipelines/items/entities_ner_transformers.py
arelight/pipelines/items/entity.py
arelight/pipelines/items/inference_bert_opennre.py
arelight/pipelines/items/inference_writer.py
arelight/pipelines/items/serializer_arekit.py
arelight/predict/__init__.py
arelight/predict/header.py
arelight/predict/provider.py
arelight-0.25.0.dist-info/LICENSE
arelight-0.25.0.dist-info/METADATA
arelight-0.25.0.dist-info/WHEEL
arelight-0.25.0.dist-info/top_level.txt
arelight-0.25.0.dist-info/RECORD
