Metadata-Version: 2.1
Name: arelight
Version: 0.25.0
Summary: About Mass-media text processing application for your Relation Extraction task, powered by AREkit.
Home-page: https://github.com/nicolay-r/ARElight
Author: Nicolay Rusnachenko
Author-email: rusnicolay@gmail.com
License: MIT License
Keywords: natural language processing,relation extraction,sentiment analysis
Classifier: Programming Language :: Python
Classifier: Programming Language :: Python :: 3.9
Classifier: Topic :: Scientific/Engineering :: Information Analysis
Classifier: Topic :: Text Processing :: Linguistic
License-File: LICENSE
Requires-Dist: deeppavlov ==1.3.0
Requires-Dist: transformers ==4.24.0
Requires-Dist: torch ==2.0.1
Requires-Dist: pytorch-crf ==0.7.2
Requires-Dist: source-iter ==0.24.2
Requires-Dist: arekit ==0.25.1
Requires-Dist: bulk-translate ==0.24.1
Requires-Dist: open-nre ==0.1.1
Requires-Dist: nltk ==3.8.1
Requires-Dist: googletrans ==3.1.0a0
Requires-Dist: httpcore ==0.9.1
Requires-Dist: argparse-to-json ==0.0.1
Requires-Dist: httpx ==0.13.3
Requires-Dist: requests
